pythf/__init__.py
pythf/client.py
pythf/const.py
pythf/error.py
pythf/pythf.py
pythf-1.0.5.dist-info/LICENSE
pythf-1.0.5.dist-info/METADATA
pythf-1.0.5.dist-info/WHEEL
pythf-1.0.5.dist-info/top_level.txt
pythf-1.0.5.dist-info/RECORD
