Metadata-Version: 2.1
Name: pythf
Version: 1.0.5
Summary: Group-IB THF REST API Python Bindings
Home-page: https://github.com/Group-IB/pythf
Author: Group-IB THF
Author-email: tds@group-ib.com
License: MIT
Keywords: security sandbox gib polygon
Platform: UNKNOWN
Classifier: Development Status :: 5 - Production/Stable
Classifier: Intended Audience :: Developers
Classifier: Topic :: Security
Classifier: License :: OSI Approved :: MIT License
Classifier: Programming Language :: Python :: 3
Classifier: Programming Language :: Python :: 3.6
Classifier: Programming Language :: Python :: 3.7
Classifier: Programming Language :: Python :: 3.8
Classifier: Programming Language :: Python :: 3.9
Requires-Dist: requests
